brawling/__init__.py
brawling/__version__.py
brawling/base_client.py
brawling/brawlapi/__init__.py
brawling/brawlapi/client.py
brawling/brawlapi/exceptions.py
brawling/brawlapi/models/__init__.py
brawling/brawlapi/models/brawlers.py
brawling/brawlapi/models/events.py
brawling/brawlapi/models/icons.py
brawling/brawlapi/models/maps.py
brawling/brawlapi/models/modes.py
brawling/client.py
brawling/exceptions.py
brawling/models/__init__.py
brawling/models/base.py
brawling/models/brawlers.py
brawling/models/clubs.py
brawling/models/events.py
brawling/models/players.py
brawling/models/rankings.py
brawling/util.py
brawling-2.0.2.dist-info/LICENSE
brawling-2.0.2.dist-info/METADATA
brawling-2.0.2.dist-info/WHEEL
brawling-2.0.2.dist-info/RECORD
