Metadata-Version: 2.1
Name: brawling
Version: 2.0.2
Summary: Brawl stars API wrapper (sync + async + proxy + brawlapi)
License: MIT
Author: dankmeme01
Author-email: divanbotinkovich@gmail.com
Requires-Python: >=3.7,<4.0
Classifier: License :: OSI Approved :: MIT License
Classifier: Programming Language :: Python :: 3
Classifier: Programming Language :: Python :: 3.7
Classifier: Programming Language :: Python :: 3.8
Classifier: Programming Language :: Python :: 3.9
Classifier: Programming Language :: Python :: 3.10
Classifier: Programming Language :: Python :: 3.11
Provides-Extra: acache
Provides-Extra: async
Provides-Extra: cache
Requires-Dist: aiohttp (>=3.8.3,<4.0.0) ; extra == "async" or extra == "acache"
Requires-Dist: aiohttp-client-cache (>=0.7.3,<0.8.0) ; extra == "acache"
Requires-Dist: aiosqlite (>=0.17.0,<0.18.0) ; extra == "acache"
Requires-Dist: python-dateutil (>=2.8.2,<3.0.0)
Requires-Dist: requests (>=2.28.1,<3.0.0)
Requires-Dist: requests-cache (>=0.9.6,<0.10.0) ; extra == "cache"
